llmfusion/__init__.py
llmfusion/core.py
llmfusion/base/__init__.py
llmfusion/base/exceptions.py
llmfusion/base/interfaces.py
llmfusion/base/models.py
llmfusion/integrations/prometheus.py
llmfusion/integrations/vault.py
llmfusion/providers/__init__.py
llmfusion/providers/claude.py
llmfusion/providers/deepseek.py
llmfusion/providers/gemini.py
llmfusion/providers/grok.py
llmfusion/providers/openai.py
llmfusion/providers/configs/model_global_configs.py
llmfusion/resources/cost_map.json
llmfusion/resources/models.json
llmfusion/utils/__init__.py
llmfusion/utils/diskcache_.py
llmfusion/utils/key_manager.py
llmfusion/utils/rate_limiter.py
llmfusion/utils/resource_loader.py
llmfusion-0.2.7.dist-info/LICENSE
llmfusion-0.2.7.dist-info/METADATA
llmfusion-0.2.7.dist-info/WHEEL
llmfusion-0.2.7.dist-info/top_level.txt
llmfusion-0.2.7.dist-info/RECORD
