Metadata-Version: 2.2
Name: llmfusion
Version: 0.2.7
Summary: Unified interface for multiple LLM providers
Author-email: Mohamed Benhaddou <mbenhaddou@mentis.io>
License: MIT
Classifier: Programming Language :: Python :: 3
Classifier: License :: OSI Approved :: MIT License
Classifier: Operating System :: OS Independent
Requires-Python: >=3.9
License-File: LICENSE
Requires-Dist: openai>=1.0
Requires-Dist: anthropic>=0.7
Requires-Dist: google-generativeai>=0.3
Requires-Dist: httpx>=0.25
Requires-Dist: pydantic>=2.0
Requires-Dist: diskcache>=5.6
Requires-Dist: tenacity>=8.2
Provides-Extra: dev
Requires-Dist: pytest; extra == "dev"
Requires-Dist: pytest-asyncio; extra == "dev"
Requires-Dist: pytest-cov; extra == "dev"
Requires-Dist: flake8; extra == "dev"
Provides-Extra: vault
Requires-Dist: hvac; extra == "vault"
